odoo8_addon_stock_valuation_account_manual_adjustment-8.0.1.0.0-py2.7-nspkg.pth
odoo_addons/stock_valuation_account_manual_adjustment/init_hook.py
odoo_addons/stock_valuation_account_manual_adjustment/__openerp__.py
odoo_addons/stock_valuation_account_manual_adjustment/__init__.py
odoo_addons/stock_valuation_account_manual_adjustment/README.rst
odoo_addons/stock_valuation_account_manual_adjustment/security/stock_valuation_account_manual_adjustment_security.xml
odoo_addons/stock_valuation_account_manual_adjustment/security/ir.model.access.csv
odoo_addons/stock_valuation_account_manual_adjustment/models/product.py
odoo_addons/stock_valuation_account_manual_adjustment/models/__init__.py
odoo_addons/stock_valuation_account_manual_adjustment/models/stock_valuation_account_manual_adjustment.py
odoo_addons/stock_valuation_account_manual_adjustment/models/account_move.py
odoo_addons/stock_valuation_account_manual_adjustment/views/account_move_line_view.xml
odoo_addons/stock_valuation_account_manual_adjustment/views/product_view.xml
odoo_addons/stock_valuation_account_manual_adjustment/views/stock_valuation_account_manual_adjustment_view.xml
odoo_addons/stock_valuation_account_manual_adjustment/wizards/mass_create.py
odoo_addons/stock_valuation_account_manual_adjustment/wizards/mass_create_view.xml
odoo_addons/stock_valuation_account_manual_adjustment/wizards/__init__.py
odoo_addons/stock_valuation_account_manual_adjustment/data/stock_valuation_account_manual_adjustment_data.xml
odoo_addons/stock_valuation_account_manual_adjustment/tests/__init__.py
odoo_addons/stock_valuation_account_manual_adjustment/tests/test_stock_valuation_account_manual_adjustment.py
odoo_addons/stock_valuation_account_manual_adjustment/static/description/icon.png
odoo8_addon_stock_valuation_account_manual_adjustment-8.0.1.0.0.dist-info/top_level.txt
odoo8_addon_stock_valuation_account_manual_adjustment-8.0.1.0.0.dist-info/WHEEL
odoo8_addon_stock_valuation_account_manual_adjustment-8.0.1.0.0.dist-info/RECORD
odoo8_addon_stock_valuation_account_manual_adjustment-8.0.1.0.0.dist-info/metadata.json
odoo8_addon_stock_valuation_account_manual_adjustment-8.0.1.0.0.dist-info/DESCRIPTION.rst
odoo8_addon_stock_valuation_account_manual_adjustment-8.0.1.0.0.dist-info/METADATA
odoo8_addon_stock_valuation_account_manual_adjustment-8.0.1.0.0.dist-info/namespace_packages.txt
